MarinegeoTemplateBuilder/__init__.py
MarinegeoTemplateBuilder/classes.py
MarinegeoTemplateBuilder/construct.py
MarinegeoTemplateBuilder/defaults.py
MarinegeoTemplateBuilder/example.py
MarinegeoTemplateBuilder/load.py
MarinegeoTemplateBuilder/marinegeo_branding.png
MarinegeoTemplateBuilder/validators.py
MarinegeoTemplateBuilder-0.1.1.dist-info/LICENSE
MarinegeoTemplateBuilder-0.1.1.dist-info/METADATA
MarinegeoTemplateBuilder-0.1.1.dist-info/WHEEL
MarinegeoTemplateBuilder-0.1.1.dist-info/top_level.txt
MarinegeoTemplateBuilder-0.1.1.dist-info/RECORD
