Metadata-Version: 2.1
Name: MarinegeoTemplateBuilder
Version: 0.1.1
Summary: Constructs MarineGEO data entry excel workbooks with built in validation
Home-page: https://github.com/MarineGEO/MarineGEO-template-builder
Author: Andy Bell
Author-email: bellan@si.edu
License: UNKNOWN
Platform: UNKNOWN
Classifier: Programming Language :: Python :: 3
Classifier: License :: OSI Approved :: MIT License
Classifier: Operating System :: OS Independent
Requires-Dist: xlsxwriter
Requires-Dist: pandas
Requires-Dist: chardet
Requires-Dist: xlrd
